[  
           
 
 

  {
           "league": "https://images.fotmob.com/image_resources/logo/leaguelogo/53.png",
            "date": "April 9",
            "time": "5:30 PM",
             "isLive": false, 
            "himg": "https://images.fotmob.com/image_resources/logo/teamlogo/9748.png",
            "aimg": "https://images.fotmob.com/image_resources/logo/teamlogo/9851.png",
            "hteam" : "Lyon",
            "ateam" : "Rennes",
            "link":[
                   {   "type": "SD ",
                       "livelink":""
                     },
                  
                   {   "type": "HD ",
                       "livelink":""
                   }
                   ]

        },        
  
  {
           "league": "https://images.fotmob.com/image_resources/logo/leaguelogo/87.png",
            "date": "April 9",
            "time": "6:30 PM",
             "isLive": false,
            "himg": "https://images.fotmob.com/image_resources/logo/teamlogo/10281.png",
            "aimg": "https://images.fotmob.com/image_resources/logo/teamlogo/8661.png",
            "hteam" : "Real Valladolid",
            "ateam" : "Malllorca",
            "link":[
                   {   "type": "SD ",
                       "livelink":""
                     },
                  
                   {   "type": "HD ",
                       "livelink":""
                   }
                   ]

        },

{
           "league": "https://images.fotmob.com/image_resources/logo/leaguelogo/47.png",
            "date": "April 9",
            "time": "7:30 PM",
             "isLive": false, 
            "himg": "https://images.fotmob.com/image_resources/logo/teamlogo/8463.png",
            "aimg": "https://images.fotmob.com/image_resources/logo/teamlogo/9826.png",
            "hteam" : "Leeds United",
            "ateam" : "Crystal Palace",
            "link":[
                   {   "type": "SD ",
                       "livelink":""
                     },
                  
                   {   "type": "HD ",
                       "livelink":""
                   }
                   ]
        }
         
         
         
         
         
         
  ]
