[ 


 {
"league": "https://images.fotmob.com/image_resources/logo/leaguelogo/87.png",
"date": "Aug 26",
"time": "12:00 AM",
"himg": "https://images.fotmob.com/image_resources/logo/teamlogo/8306.png",
"aimg": "https://images.fotmob.com/image_resources/logo/teamlogo/8560.png",
"isLive":false,
"hteam" : "Las Palmas",
"ateam" : "Real Sociedad",

"link":[
      {
     "type": "SD",
     "livelink":""
       },
      {
      "type": "HD",
      "livelink":""
       },
       {
      "type": "FHD",
      "livelink":""
       }
       ] 
       },
      
 {
"league": "https://images.fotmob.com/image_resources/logo/leaguelogo/54.png",
"date": "Aug 26",
"time": "1:00 AM",
"himg": "https://images.fotmob.com/image_resources/logo/teamlogo/178475.png",
"aimg": "https://images.fotmob.com/image_resources/logo/teamlogo/10269.png",
"isLive":false,
"hteam" : "RB Leipzig",
"ateam" : "VfB Stuttgart",

"link":[
      {
     "type": "SD",
     "livelink":""
       },
      {
      "type": "HD",
      "livelink":""
       },
       {
      "type": "FHD",
      "livelink":""
       }
       ] 
       },
      
 {
"league": "https://images.fotmob.com/image_resources/logo/leaguelogo/47.png",
"date": "Aug 26",
"time": "1:30 AM",
"himg": "https://images.fotmob.com/image_resources/logo/teamlogo/8455.png",
"aimg": "https://images.fotmob.com/image_resources/logo/teamlogo/8346.png",
"isLive":false,
"hteam" : "Chelsea",
"ateam" : "Luton",

"link":[
      {
     "type": "SD",
     "livelink":""
       },
      {
      "type": "HD",
      "livelink":""
       },
       {
      "type": "FHD",
      "livelink":""
       }
       ] 
       },
      
 {
"league": "https://images.fotmob.com/image_resources/logo/leaguelogo/53.png",
"date": "Aug 26",
"time": "1:30 AM",
"himg": "https://images.fotmob.com/image_resources/logo/teamlogo/9830.png",
"aimg": "https://images.fotmob.com/image_resources/logo/teamlogo/9829.png",
"isLive":false,
"hteam" : "Nantes",
"ateam" : "Monaco",

"link":[
      {
     "type": "SD",
     "livelink":""
       },
      {
      "type": "HD",
      "livelink":""
       },
       {
      "type": "FHD",
      "livelink":""
       }
       ] 
       },
      
 {
"league": "https://images.fotmob.com/image_resources/logo/leaguelogo/87.png",
"date": "Aug 26",
"time": "2:00 AM",
"himg": "https://images.fotmob.com/image_resources/logo/teamlogo/9910.png",
"aimg": "https://images.fotmob.com/image_resources/logo/teamlogo/8633.png",
"isLive":false,
"hteam" : "Celta Vigo",
"ateam" : "Real Madrid",

"link":[
      {
     "type": "SD",
     "livelink":""
       },
      {
      "type": "HD",
      "livelink":""
       },
       {
      "type": "FHD",
      "livelink":""
       }
       ] 
       },
      
 {
"league": "https://images.fotmob.com/image_resources/logo/leaguelogo/53.png",
"date": "Aug 26",
"time": " 6:00PM",
"himg": "https://images.fotmob.com/image_resources/logo/teamlogo/9830.png",
"aimg": "https://images.fotmob.com/image_resources/logo/teamlogo/9829.png",
"isLive":false,
"hteam" : "Bournemouth",
"ateam" : "Tottenham",

"link":[
      {
     "type": "SD",
     "livelink":""
       },
      {
      "type": "HD",
      "livelink":""
       },
       {
      "type": "FHD",
      "livelink":""
       }
       ] 
       },
      
 {
"league": "https://images.fotmob.com/image_resources/logo/leaguelogo/87.png",
"date": "Aug 26",
"time": "8:00 PM",
"himg": "https://images.fotmob.com/image_resources/logo/teamlogo/9910.png",
"aimg": "https://images.fotmob.com/image_resources/logo/teamlogo/8633.png",
"isLive":false,
"hteam" : "VfL Bochum",
"ateam" : "Dortmund",

"link":[
      {
     "type": "SD",
     "livelink":""
       },
      {
      "type": "HD",
      "livelink":""
       },
       {
      "type": "FHD",
      "livelink":""
       }
       ] 
       },
      
 {
"league": "https://images.fotmob.com/image_resources/logo/leaguelogo/87.png",
"date": "Aug 26",
"time": "8:00 PM",
"himg": "https://images.fotmob.com/image_resources/logo/teamlogo/9910.png",
"aimg": "https://images.fotmob.com/image_resources/logo/teamlogo/8633.png",
"isLive":false,
"hteam" : "SV Darmstadt"
"ateam" : "Union Berlin",

"link":[
      {
     "type": "SD",
     "livelink":""
       },
      {
      "type": "HD",
      "livelink":""
       },
       {
      "type": "FHD",
      "livelink":""
       }
       ] 
       },
      
 {
"league": "https://images.fotmob.com/image_resources/logo/leaguelogo/87.png",
"date": "Aug 26",
"time": "8:00 PM",
"himg": "https://images.fotmob.com/image_resources/logo/teamlogo/9910.png",
"aimg": "https://images.fotmob.com/image_resources/logo/teamlogo/8633.png",
"isLive":false,
"hteam" : "FC Heidenheim",
"ateam" : "Hoffenheim",

"link":[
      {
     "type": "SD",
     "livelink":""
       },
      {
      "type": "HD",
      "livelink":""
       },
       {
      "type": "FHD",
      "livelink":""
       }
       ] 
       },
      
 {
"league": "https://images.fotmob.com/image_resources/logo/leaguelogo/87.png",
"date": "Aug 26",
"time": "8:00 PM",
"himg": "https://images.fotmob.com/image_resources/logo/teamlogo/9910.png",
"aimg": "https://images.fotmob.com/image_resources/logo/teamlogo/8633.png",
"isLive":false,
"hteam" : "Koln",
"ateam" : "Wolfsburg",

"link":[
      {
     "type": "SD",
     "livelink":""
       },
      {
      "type": "HD",
      "livelink":""
       },
       {
      "type": "FHD",
      "livelink":""
       }
       ] 
       },
      
 {
"league": "https://images.fotmob.com/image_resources/logo/leaguelogo/87.png",
"date": "Aug 26",
"time": "8:00 PM",
"himg": "https://images.fotmob.com/image_resources/logo/teamlogo/9910.png",
"aimg": "https://images.fotmob.com/image_resources/logo/teamlogo/8633.png",
"isLive":false,
"hteam" : "Freiburg",
"ateam" : "Werder Bremen",

"link":[
      {
     "type": "SD",
     "livelink":""
       },
      {
      "type": "HD",
      "livelink":""
       },
       {
      "type": "FHD",
      "livelink":""
       }
       ] 
       }
]
     
     
      
 

        
   
   
   
   
 


 


 




